impulse/__init__.py
impulse/api_sdk/__init__.py
impulse/api_sdk/api_key.py
impulse/api_sdk/billing.py
impulse/api_sdk/dataset.py
impulse/api_sdk/exceptions.py
impulse/api_sdk/fine_tuning.py
impulse/api_sdk/model.py
impulse/api_sdk/models.py
impulse/api_sdk/sdk.py
impulse/api_sdk/usage.py
impulse/api_sdk/user.py
impulse_api_sdk_python-0.11.1.dist-info/licenses/LICENSE.md
impulse_api_sdk_python-0.11.1.dist-info/METADATA
impulse_api_sdk_python-0.11.1.dist-info/WHEEL
impulse_api_sdk_python-0.11.1.dist-info/top_level.txt
impulse_api_sdk_python-0.11.1.dist-info/RECORD
