Metadata-Version: 2.4
Name: impulse-api-sdk-python
Version: 0.11.1
Summary: A Python SDK for interacting with the Impulse Labs API
Home-page: https://github.com/impulselabs/api-sdk-python
Author: Impulse Labs AI
Author-email: engg@impulselabs.ai
License: MIT
Requires-Python: >=3.10
License-File: LICENSE.md
Requires-Dist: aiohttp
Requires-Dist: pydantic
Requires-Dist: pydantic[email]
Dynamic: author
Dynamic: author-email
Dynamic: description
Dynamic: description-content-type
Dynamic: home-page
Dynamic: license
Dynamic: license-file
Dynamic: requires-dist
Dynamic: requires-python
Dynamic: summary
